{
  "message": "SYSTEM: {\n    \"format\": \"PDF 1.5\",\n    \"title\": \"Linked Games\",\n    \"author\": \"Janne Parkkila\",\n    \"subject\": \"\",\n    \"keywords\": \"\",\n    \"creator\": \"Microsoft速 PowerPoint速 2013\",\n    \"producer\": \"Microsoft速 PowerPoint速 2013\",\n    \"creationDate\": \"D:20131003101559+02'00'\",\n    \"modDate\": \"D:20131003101559+02'00'\",\n    \"trapped\": \"\",\n    \"encryption\": null\n}",
  "speaker": "SYSTEM",
  "uuid": "6dbb5c6f-7fb2-4b2d-bf1c-9d01da8d2dab"
}