{
  "message": "SYSTEM: {\n    \"format\": \"PDF 1.7\",\n    \"title\": \"Web 3.0 Folksonomias y Ontologías  Estado del Arte y Propuesta de Investigación\",\n    \"author\": \"Héctor Andrés García\",\n    \"subject\": \"\",\n    \"keywords\": \"\",\n    \"creator\": \"Microsoft® PowerPoint® for Microsoft 365\",\n    \"producer\": \"Microsoft® PowerPoint® for Microsoft 365\",\n    \"creationDate\": \"D:20241107101248+01'00'\",\n    \"modDate\": \"D:20241107101248+01'00'\",\n    \"trapped\": \"\",\n    \"encryption\": null\n}",
  "speaker": "SYSTEM",
  "uuid": "aed0a8f7-5548-4cd6-82b6-45c9c3c618f1"
}