{
  "message": "SYSTEM: {\n    \"format\": \"PDF 1.4\",\n    \"title\": \"Sin título de diapositiva\",\n    \"author\": \"Simon\",\n    \"subject\": \"\",\n    \"keywords\": \"\",\n    \"creator\": \"Acrobat PDFMaker 8.1 para PowerPoint\",\n    \"producer\": \"Acrobat Distiller 8.1.0 (Windows)\",\n    \"creationDate\": \"D:20101115110215+01'00'\",\n    \"modDate\": \"D:20101115110218+01'00'\",\n    \"trapped\": \"\",\n    \"encryption\": null\n}",
  "speaker": "SYSTEM",
  "uuid": "d0473ed0-f4ee-4336-a83a-145437d0eace"
}