{
  "message": "SYSTEM: GeoLinkedData%28v1-boris%29.pdf metadatos {\n    \"format\": \"PDF 1.5\",\n    \"title\": \"Microsoft PowerPoint - GeoLinkedData(v1-boris).pptx\",\n    \"author\": \"boricles\",\n    \"subject\": \"\",\n    \"keywords\": \"\",\n    \"creator\": \"PScript5.dll Version 5.2.2\",\n    \"producer\": \"Acrobat Distiller 9.3.3 (Windows)\",\n    \"creationDate\": \"D:20101206141815+01'00'\",\n    \"modDate\": \"D:20101206141815+01'00'\",\n    \"trapped\": \"\",\n    \"encryption\": null\n}",
  "speaker": "SYSTEM",
  "uuid": "1275b885-c6b9-4354-8568-b468e19fe69e"
}