{
  "message": "SYSTEM: Metodolog%C3%ADa-2-v2.pdf metadatos {\n    \"format\": \"PDF 1.4\",\n    \"title\": \"Microsoft PowerPoint - Metodología-2-v2(boris).ppt [Compatibility Mode]\",\n    \"author\": \"boricles\",\n    \"subject\": \"\",\n    \"keywords\": \"\",\n    \"creator\": \"PScript5.dll Version 5.2.2\",\n    \"producer\": \"Acrobat Distiller 7.0.5 (Windows)\",\n    \"creationDate\": \"D:20091119171049+01'00'\",\n    \"modDate\": \"D:20091119171049+01'00'\",\n    \"trapped\": \"\",\n    \"encryption\": null\n}",
  "speaker": "SYSTEM",
  "uuid": "14af132f-a4f8-4e18-b9d3-6c079bd3c664"
}