{
  "message": "SYSTEM: AMPER08_-_Introduction_to_SPARQL.pdf metadatos {\n    \"format\": \"PDF 1.7\",\n    \"title\": \"WP1.6\",\n    \"author\": \"Angel López Cima\",\n    \"subject\": \"\",\n    \"keywords\": \"\",\n    \"creator\": \"Microsoft® PowerPoint® for Microsoft 365\",\n    \"producer\": \"Microsoft® PowerPoint® for Microsoft 365\",\n    \"creationDate\": \"D:20241107135648+01'00'\",\n    \"modDate\": \"D:20241107135648+01'00'\",\n    \"trapped\": \"\",\n    \"encryption\": null\n}",
  "speaker": "SYSTEM",
  "uuid": "498cd6b4-b374-4177-806b-cd08061cc4b9"
}