{
  "message": "SYSTEM: PatriciaMart%C3%ADn.pdf metadatos {\n    \"format\": \"PDF 1.7\",\n    \"title\": \"Presentación de PowerPoint\",\n    \"author\": \"Patricia Martín Chozas\",\n    \"subject\": \"\",\n    \"keywords\": \"\",\n    \"creator\": \"Microsoft® PowerPoint® 2016\",\n    \"producer\": \"Microsoft® PowerPoint® 2016\",\n    \"creationDate\": \"D:20180614144549+02'00'\",\n    \"modDate\": \"D:20180614144549+02'00'\",\n    \"trapped\": \"\",\n    \"encryption\": null\n}",
  "speaker": "SYSTEM",
  "uuid": "58cb1e5b-62a1-48be-9c7d-272fb56fa56e"
}