{
  "message": "SYSTEM: CV-Cicyt_Charo_enero2009.pdf metadatos {\n    \"format\": \"PDF 1.4\",\n    \"title\": \"CV-Cicyt_Charo_enero2009\",\n    \"author\": \"jasala\",\n    \"subject\": \"\",\n    \"keywords\": \"\",\n    \"creator\": \"PDFCreator Version 0.9.5\",\n    \"producer\": \"GPL Ghostscript 8.61\",\n    \"creationDate\": \"D:20100119164640+01'00'\",\n    \"modDate\": \"D:20100119164640+01'00'\",\n    \"trapped\": \"\",\n    \"encryption\": null\n}",
  "speaker": "SYSTEM",
  "uuid": "e19a82af-6ed5-4d20-8f2f-4487459a2e25"
}