{
  "message": "SYSTEM: HydrOntology_LuisMVilches.pdf metadatos {\n    \"format\": \"PDF 1.7\",\n    \"title\": \"Metodología para la integración de información basada en ontologías de bases de datos heterogéneas  en el dominio hidrográfico\",\n    \"author\": \"Luis Manuel Vilches Blázquez\",\n    \"subject\": \"\",\n    \"keywords\": \"\",\n    \"creator\": \"Microsoft® PowerPoint® for Microsoft 365\",\n    \"producer\": \"Microsoft® PowerPoint® for Microsoft 365\",\n    \"creationDate\": \"D:20241107135705+01'00'\",\n    \"modDate\": \"D:20241107135705+01'00'\",\n    \"trapped\": \"\",\n    \"encryption\": null\n}",
  "speaker": "SYSTEM",
  "uuid": "e9ce3d99-8647-43c9-ae15-e03f1a7580da"
}