{
  "message": "SYSTEM: OWL-API-v1.pdf metadatos {\n    \"format\": \"PDF 1.7\",\n    \"title\": \"Sin título de diapositiva\",\n    \"author\": \"MC\",\n    \"subject\": \"\",\n    \"keywords\": \"\",\n    \"creator\": \"Microsoft® PowerPoint® for Microsoft 365\",\n    \"producer\": \"Microsoft® PowerPoint® for Microsoft 365\",\n    \"creationDate\": \"D:20250109122029+01'00'\",\n    \"modDate\": \"D:20250109122029+01'00'\",\n    \"trapped\": \"\",\n    \"encryption\": null\n}",
  "speaker": "SYSTEM",
  "uuid": "c232add6-d646-40d4-9904-06eedb176c42"
}